shasta/__init__.py
shasta/ast_node.py
shasta/ast_walker.py
shasta/bash_to_shasta_ast.py
shasta/flags.py
shasta/gosh_to_shasta_ast.py
shasta/json_to_ast.py
shasta/print_lib.py
shasta/subst.py
shasta-0.4.dist-info/licenses/LICENSE
shasta-0.4.dist-info/METADATA
shasta-0.4.dist-info/WHEEL
shasta-0.4.dist-info/top_level.txt
shasta-0.4.dist-info/RECORD
