Metadata-Version: 2.4
Name: shasta
Version: 0.4
Summary: A shell AST library in Python
Author-email: Konstantinos Kallas <konstantinos.kallas@hotmail.com>
License: MIT License
Project-URL: Homepage, https://github.com/binpash/shasta
Project-URL: Bug Tracker, https://github.com/binpash/shasta/issues
Classifier: Programming Language :: Python :: 3
Classifier: Topic :: System :: System Shells
Classifier: License :: OSI Approved :: MIT License
Classifier: Operating System :: POSIX
Requires-Python: >=3.8
License-File: LICENSE
Provides-Extra: dev
Requires-Dist: libbash; extra == "dev"
Requires-Dist: libdash; extra == "dev"
Dynamic: license-file
Dynamic: requires-python
